pathmatcher/__init__.py
pathmatcher/_version.py
pathmatcher/expandhelper.m
pathmatcher/functionalcoreg.m
pathmatcher/pathmatcher.py
pathmatcher/realignhelper.m
pathmatcher/regex_files.m
pathmatcher/reorientation_registration_helper.py
pathmatcher/reorienthelper.m
pathmatcher/tee.py
pathmatcher/mlabwrap/README.rst
pathmatcher/mlabwrap/__init__.py
pathmatcher/mlabwrap/awmstools.py
pathmatcher/mlabwrap/matlabcom.py
pathmatcher/mlabwrap/matlabpipe.py
pathmatcher/mlabwrap/mlabraw.py
pathmatcher/mlabwrap/mlabwrap.py
pathmatcher/pathlib2/__init__.py
pathmatcher-1.8.8.dist-info/LICENSE
pathmatcher-1.8.8.dist-info/METADATA
pathmatcher-1.8.8.dist-info/WHEEL
pathmatcher-1.8.8.dist-info/entry_points.txt
pathmatcher-1.8.8.dist-info/top_level.txt
pathmatcher-1.8.8.dist-info/RECORD
