Metadata-Version: 2.2
Name: pathmatcher
Version: 1.8.8
Summary: Regular Expression Path Matcher - Easily batch manipulate folders and files trees with regular expression!
Author-email: Stephen Karl Larroque <lrq3000@gmail.com>
Maintainer-email: Stephen Karl Larroque <lrq3000@gmail.com>
License: MIT License
Project-URL: Homepage, https://github.com/lrq3000/pathmatcher
Project-URL: Documentation, https://github.com/lrq3000/pathmatcher/blob/master/README.md
Project-URL: Source, https://github.com/lrq3000/pathmatcher
Project-URL: Tracker, https://github.com/lrq3000/pathmatcher/issues
Project-URL: Download, https://github.com/lrq3000/pathmatcher/releases
Keywords: file,folders,manipulation,copy,move,delete,batch,regex,regexp,regular expression,regular expressions,file trees,file tree,files tree,files trees,neuroimaging,mri,fmri,nifti,nii,reorientation,spm
Classifier: Development Status :: 6 - Mature
Classifier: License :: OSI Approved :: MIT License
Classifier: Environment :: Console
Classifier: Operating System :: Microsoft :: Windows
Classifier: Operating System :: MacOS :: MacOS X
Classifier: Operating System :: POSIX :: Linux
Classifier: Environment :: Console
Classifier: Intended Audience :: Developers
Classifier: Intended Audience :: Healthcare Industry
Classifier: Intended Audience :: Science/Research
Classifier: Intended Audience :: System Administrators
Classifier: Programming Language :: Python
Classifier: Programming Language :: Python :: 3
Classifier: Programming Language :: Python :: 3.7
Classifier: Programming Language :: Python :: 3.8
Classifier: Programming Language :: Python :: 3.9
Classifier: Programming Language :: Python :: 3.10
Classifier: Programming Language :: Python :: 3.11
Classifier: Programming Language :: Python :: 3.12
Classifier: Programming Language :: Python :: Implementation :: PyPy
Classifier: Topic :: Software Development :: Libraries
Classifier: Topic :: Software Development :: Libraries :: Python Modules
Classifier: Topic :: Utilities
Requires-Python: >=3.7
License-File: LICENSE
Requires-Dist: chardet>=3.0.4
Requires-Dist: tqdm>=4.46.0
Requires-Dist: scandir>=1.10.0
Requires-Dist: future
Provides-Extra: test
Requires-Dist: pytest; extra == "test"
Requires-Dist: pytest-cov; extra == "test"
Requires-Dist: py3make; extra == "test"
Provides-Extra: testmeta
Requires-Dist: build; extra == "testmeta"
Requires-Dist: twine; extra == "testmeta"
Requires-Dist: validate-pyproject; extra == "testmeta"
Requires-Dist: rstcheck; extra == "testmeta"
